cleankit/__init__.py
cleankit/mail.py
cleankit-0.0.5.dist-info/METADATA
cleankit-0.0.5.dist-info/WHEEL
cleankit-0.0.5.dist-info/top_level.txt
cleankit-0.0.5.dist-info/RECORD
