Metadata-Version: 2.1
Name: cleankit
Version: 0.0.5
Summary: Simple operations for navigation
Home-page: https://github.com/cubelogistics/cleankit
Author: Sacha Ichbiah
Author-email: sacha@cu6e.com
Project-URL: Team website, https://github.com/cubelogistics
Classifier: Programming Language :: Python :: 3
Classifier: License :: OSI Approved :: MIT License
Classifier: Operating System :: POSIX :: Linux
Classifier: Operating System :: MacOS
Classifier: Intended Audience :: Science/Research
Requires-Python: >=3.6
Requires-Dist: pandas
Requires-Dist: tqdm
Requires-Dist: pydantic
Requires-Dist: phonenumbers
Requires-Dist: python-stdnum
Requires-Dist: numpy
